nonebot_plugin_shutdown_hook/__init__.py
nonebot_plugin_shutdown_hook-0.1.2.dist-info/METADATA
nonebot_plugin_shutdown_hook-0.1.2.dist-info/WHEEL
nonebot_plugin_shutdown_hook-0.1.2.dist-info/RECORD
