Metadata-Version: 2.1
Name: nonebot-plugin-shutdown-hook
Version: 0.1.2
Summary: 高优先级关闭信号钩子插件
Home-page: https://github.com/Sclock/nonebot-plugin-shutdown-hook
License: MIT
Keywords: nonebot,plugin,shutdown,hook
Author: Sclock
Author-email: 1342810270@qq.com
Requires-Python: >=3.9
Classifier: License :: OSI Approved :: MIT License
Classifier: Programming Language :: Python :: 3
Classifier: Programming Language :: Python :: 3.9
Classifier: Programming Language :: Python :: 3.10
Classifier: Programming Language :: Python :: 3.11
Classifier: Programming Language :: Python :: 3.12
Requires-Dist: nonebot2 (>=2.0.0)
Requires-Dist: uvicorn (>=0.20.0)
Project-URL: Documentation, https://github.com/Sclock/nonebot-plugin-shutdown-hook
Project-URL: Repository, https://github.com/Sclock/nonebot-plugin-shutdown-hook
